{
	"class" : {
		"columns:" : "jm 1/13/2021 13:11",
		"empty" : "jm 1/13/2021 13:13",
		"fromCsv:fileNamed:" : "jm 1/1/2021 21:53",
		"fromCsv:stream:" : "jm 1/13/2021 13:12",
		"fromFileName:" : "jm 12/28/2020 22:41",
		"fromJsonFileName:" : "jm 12/29/2020 21:49",
		"fromJsonLinesFileNamed:" : "jm 12/29/2020 21:51",
		"fromJsonLinesStream:" : "jm 12/31/2020 22:09",
		"fromJsonStream:" : "jm 12/31/2020 12:09",
		"mergeColumns:" : "jm 12/26/2020 09:01",
		"records:" : "jm 1/13/2021 13:12",
		"rows:" : "jm 1/13/2021 13:12",
		"rows:columns:" : "jm 1/13/2021 13:12" },
	"instance" : {
		"addRecords:" : "jm 1/4/2021 09:48",
		"addRows:" : "jm 1/4/2021 09:48",
		"at:" : "jm 12/22/2020 16:02",
		"at:ifAbsent:" : "jm 1/4/2021 09:48",
		"at:put:" : "jm 1/4/2021 09:48",
		"at:update:" : "jm 1/2/2021 10:03",
		"cast:as:" : "jm 1/4/2021 15:19",
		"columnDoesNotExist" : "jm 12/21/2020 22:57",
		"columns" : "jm 12/22/2020 21:17",
		"cut:" : "jm 1/13/2021 13:11",
		"data" : "jm 12/22/2020 21:17",
		"drop:" : "jm 12/31/2020 13:20",
		"dropDuplicate:keep:" : "jm 1/4/2021 09:53",
		"dropNA" : "jm 1/4/2021 09:49",
		"first:" : "jm 1/4/2021 09:49",
		"includes:" : "jm 12/31/2020 13:18",
		"indexOfColumn:" : "jm 12/31/2020 13:10",
		"indexOfColumn:ifAbsent:" : "jm 12/31/2020 13:10",
		"initialize" : "jm 1/4/2021 09:51",
		"initializeWithColumnNames:" : "jm 1/4/2021 13:22",
		"initializeWithColumnValues:" : "jm 1/4/2021 13:24",
		"initializeWithColumns:" : "jm 1/4/2021 13:36",
		"initializeWithData:columns:index:" : "jm 1/4/2021 09:51",
		"initializeWithRecords:" : "jm 12/31/2020 14:25",
		"initializeWithRows:" : "jm 12/31/2020 14:25",
		"initializeWithRows:columns:" : "jm 1/4/2021 13:24",
		"innerJoin:on:" : "jm 12/25/2020 21:51",
		"innerJoin:on:and:" : "jm 1/4/2021 13:25",
		"isEmpty" : "jm 12/24/2020 22:53",
		"last:" : "jm 1/4/2021 09:49",
		"leftJoin:on:" : "jm 12/26/2020 00:37",
		"leftJoin:on:and:" : "jm 1/4/2021 13:25",
		"notEmpty" : "jm 12/24/2020 22:52",
		"primaryIndex" : "jm 1/10/2021 13:48",
		"printAsCsv:on:" : "jm 1/4/2021 12:58",
		"printAsCsvOn:" : "jm 12/24/2020 11:24",
		"printAsJsonLinesOn:" : "jm 12/23/2020 16:14",
		"printAsJsonOn:" : "jm 12/23/2020 16:09",
		"printOn:" : "jm 12/24/2020 11:18",
		"rankBy:" : "jm 12/29/2020 11:19",
		"recordAt:" : "jm 1/4/2021 09:50",
		"recordStream" : "jm 12/27/2020 22:28",
		"recordsDo:" : "jm 12/31/2020 19:24",
		"reduce:groupedBy:" : "jm 1/13/2021 13:11",
		"rename:to:" : "jm 1/4/2021 09:52",
		"reversed" : "jm 1/4/2021 09:50",
		"rightJoin:on:" : "jm 12/26/2020 00:42",
		"rightJoin:on:and:" : "jm 1/4/2021 13:25",
		"rowAt:" : "jm 1/4/2021 09:50",
		"rowStream" : "jm 12/25/2020 13:38",
		"rowsDo:" : "jm 12/31/2020 19:24",
		"scan:for:" : "jm 1/4/2021 09:54",
		"scan:from:" : "jm 1/4/2021 09:54",
		"scan:from:to:" : "jm 1/4/2021 09:54",
		"scan:to:" : "jm 1/4/2021 09:54",
		"secondaryIndex:" : "jm 1/7/2021 16:21",
		"select:" : "jm 1/4/2021 09:50",
		"shape" : "jm 1/4/2021 09:51",
		"size" : "jm 12/22/2020 21:21",
		"sortedBy:" : "jm 12/25/2020 16:40",
		"sortedBy:ascending:" : "jm 1/2/2021 11:18",
		"sortedBy:with:" : "jm 1/10/2021 10:30",
		"streamRecords:" : "jm 12/31/2020 18:42",
		"streamRows:" : "jm 12/31/2020 18:42",
		"union:" : "jm 12/27/2020 22:27",
		"unionAll:" : "jm 1/4/2021 14:24",
		"writeAsCsv:toFileNamed:" : "jm 1/1/2021 22:14" } }
